decent_optim_wrapper/__init__.py
decent_optim_wrapper/topo.py
decent_optim_wrapper/wrapper.py
decent_optim_wrapper-0.1.1.dist-info/WHEEL
decent_optim_wrapper-0.1.1.dist-info/METADATA
decent_optim_wrapper-0.1.1.dist-info/RECORD
