Metadata-Version: 2.3
Name: decent-optim-wrapper
Version: 0.1.1
Summary: A wrapper for optimizers in PyTorch to enable decentralized training
Author: Zesen Wang
Author-email: Zesen Wang <zesen@kth.se>
Requires-Dist: loguru>=0.7.3
Requires-Dist: torch>=2.8.0
Requires-Dist: torchvision>=0.23.0
Requires-Python: >=3.12
